dla_ideal/__init__.py
dla_ideal/cli.py
dla_ideal/core/__init__.py
dla_ideal/core/solver.py
dla_ideal/io/__init__.py
dla_ideal/io/config_manager.py
dla_ideal/io/data_handler.py
dla_ideal/utils/__init__.py
dla_ideal/utils/logger.py
dla_ideal/utils/timer.py
dla_ideal/visualization/__init__.py
dla_ideal/visualization/animator.py
dla_ideal_solver-0.0.4.dist-info/LICENSE
dla_ideal_solver-0.0.4.dist-info/METADATA
dla_ideal_solver-0.0.4.dist-info/WHEEL
dla_ideal_solver-0.0.4.dist-info/entry_points.txt
dla_ideal_solver-0.0.4.dist-info/RECORD
